{
  "id": 1,
  "lessonNumber": 1,
  "versionCode": 1,
  "quarter": "2T2020",
  "title": "<p><strong>LA SINGULARIDAD DE LA BIBLIA </strong></p>",
  "color": "",
  "lessonType": "A",
  "language": "es",
  "verse": "<p><strong><span style=\"color: rgb(209, 72, 65);\">“Lámpara es a mis pies tu palabra, y lumbrera a mi camino” (Sal. 119:105).</span></strong></p>",
  "weekDate": "28 de Marzo–3 de Abril",
  "lessonDays": [
    {
      "id": 11,
      "idLesson": 1,
      "idDay": 1,
      "dayTitle": "",
      "date": "28 de Marzo",
      "verses": [
        {
          "verse": "",
          "verseText": ""
        }
      ],
      "lessonText": "<p><strong>LEE PARA EL ESTUDIO DE ESTA SEMANA:</strong></p> <p>Deuteronomio 32:45-47; Génesis 49:8-12; Isaías 53:3-7; 1 Corintios 15:3-5, 51-55; Romanos 12:2.&nbsp;</p> <p>Compuesta por 66 libros y escrita durante más de 1.500 años en tres continentes (Asia, África y Europa), por más de 40 autores, la Biblia es única. No hay otro libro, sagrado ni religioso, como este. Y no es de extrañar. Al fin y al cabo, es la Palabra de Dios.</p> <p>Hay más de 24.600 manuscritos del Nuevo Testamento que se conservan de los primeros cuatro siglos después de Cristo. De los manuscritos originales de Platón, hay 7; de Herodoto, 8; y de La Ilíada, de Homero, un poco más: son 263 copias las que perduraron. Por lo tanto, tenemos una poderosa evidencia que confirma la integridad del texto del Nuevo Testamento.</p> <p>La Biblia fue el primer libro en traducirse, el primer libro impreso en Occidente, y el primer libro cuya distribución fue tan amplia y en tantos idiomas que, en la actualidad, el 95 por ciento de la población puede leerlo.</p> <p>La Biblia también es única por su contenido y su mensaje, los cuales se centran en los actos redentores de Dios a través de la historia. Es la Palabra viva de Dios, porque los creyentes de hoy cuentan con la promesa de que el mismo Espíritu de Dios que inspiró la Escritura (2 Tim. 3:16, 17) los guiará a toda verdad a medida que estudien la Palabra (Juan 14:16, 17; 15:26; 16:13)</p>"
    },
    {
      "id": 12,
      "idLesson": 1,
      "idDay": 2,
      "dayTitle": "<p><strong>LA SINGULARLA PALABRA VIVA DE DIOS</strong></p>",
      "date": "29 de Marzo",
      "verses": [
        {
          "verse": "",
          "verseText": ""
        }
      ],
      "lessonText": "<p>Las palabras más importantes que se dicen, a menudo, son las últimas palabras que una persona pronuncia. Moisés, autor de los primeros cinco libros –y fundacionales– de la Biblia, entona un cántico al pueblo justo antes de su muerte (Deut. 31:30-32:43).</p>\n<p><strong>&nbsp;Lee Deuteronomio 32:45 al 47. ¿Cómo describe Moisés la Palabra de Dios y su poder en la vida de los hebreos que están a punto de entrar en la Tierra Prometida?</strong></p>\n<p><strong>Deuteronomio 32:45 al 47:</strong></p>\n<p><strong>45&nbsp;</strong>Cuando terminó, les dijo a todos los israelitas:&nbsp;</p>\n<p><strong>46</strong> «Mediten bien en todo lo que les he declarado solemnemente este día, y díganles a sus hijos que obedezcan fielmente todas las palabras de esta ley.</p>\n<p><strong>47&nbsp;</strong>Porque no son palabras vanas para ustedes, sino que de ellas depende su vida; por ellas vivirán mucho tiempo en el territorio que van a poseer al otro lado del Jordán».</p>\n<p>Entre las últimas palabras de Moisés, se encuentra una fuerte exhortación. Al fijar las palabras que Dios había hablado a través de él en el corazón del pueblo, Moisés quería enfatizarles que debían seguir dándole prioridad a Dios en su vida, y a su voluntad. Al comunicarles estas palabras a sus hijos, cada generación transmitiría el plan de salvación del Pacto de Dios. Fíjate que no debían elegir las palabras, sino que debían observar u obedecer “todas las palabras de esta ley” (Deut. 32:46).</p>\n<p>Al final de la historia de la Tierra, Dios tendrá un pueblo que se mantendrá fiel a todas las Escrituras, lo que implica guardar los mandamientos de Dios y tener la fe de Jesús (Apoc. 14:12). Este pueblo permanecerá fiel a la enseñanza de la Biblia, porque esta no solo garantiza una vida más abundante en la Tierra, sino un destino eterno en el hogar que Jesús está preparando para nosotros (Juan 14:1-3).</p>\n<p><strong>Lee Juan 1:1 al 5 y 14; y 14:6. ¿Qué nos enseñan estos versículos sobre Jesús y la vida eterna? ¿Qué relación hay entre el Verbo hecho carne y la revelación y la inspiración de las Escrituras?</strong></p>\n<p><strong>Juan 1:1 al 5:</strong></p>\n<p><strong>1</strong> En el principio ya existía el Verbo, y el Verbo estaba con Dios, y el Verbo era Dios.</p>\n<p><strong>2&nbsp;</strong>Él estaba con Dios en el principio.</p>\n<p><strong>3&nbsp;</strong>Por medio de él todas las cosas fueron creadas; sin él, nada de lo creado llegó a existir.</p>\n<p><strong>4&nbsp;</strong>En él estaba la vida, y la vida era la luz de la humanidad.</p>\n<p><strong>5&nbsp;</strong>Esta luz resplandece en las tinieblas, y las tinieblas no han podido extinguirla</p>\n<p><strong>Juan 1:14</strong></p>\n<p><strong>14</strong> Y el Verbo se hizo hombre y habitó[a] entre nosotros. Y hemos contemplado su gloria, la gloria que corresponde al Hijo unigénito del Padre, lleno de gracia y de verdad.</p>\n<p><strong>Juan 14:6.&nbsp;</strong></p>\n<p><strong>6&nbsp;</strong>—Yo soy el camino, la verdad y la vida —le contestó Jesús—. Nadie llega al Padre sino por mí<strong>.</strong></p>\n<p>Jesús es el centro y el objetivo de todas las Escrituras. Su encarnación como el Mesías fue el cumplimiento de las promesas del Antiguo Testamento. Debido a que él vivió, murió y resucitó, tenemos la confirmación de las Escrituras y aún más: la gran promesa de la vida eterna en una existencia completamente nueva.</p>\n<p><span style=\"color: rgb(0, 0, 0);\"><strong>Vuelve a leer Deuteronomio 32:47. En tu experiencia, ¿cuán cierto es que la obediencia a la Palabra de Dios “no [te] es cosa vana”? ¿Por qué la fe en Dios y la obediencia a su Palabra nunca son en vano?</strong></span></p>"
    },
    {
      "id": 13,
      "idLesson": 1,
      "idDay": 3,
      "dayTitle": "<p><strong>¿QUIÉN ESCRIBIÓ LA BIBLIA, Y DÓNDE?</strong></p>",
      "date": "30 de Marzo",
      "verses": [
        {
          "verse": "",
          "verseText": ""
        }
      ],
      "lessonText": "<p>La diversidad de autores, así como sus ubicaciones y antecedentes, brindan un testimonio único de que Dios obra para comunicar la historia y su mensaje a personas culturalmente tan diversas como la audiencia a la que están dirigidos.</p>\n<p><strong>¿Qué nos dicen los siguientes versículos sobre los escritores bíblicos y su contexto? (Éxo. 2:10; Amós 7:14; Jer. 1:1-6; Dan. 6:1-5; Mat. 9:9; Fil. 3:3-6; Apoc. 1:9).</strong></p>\n<p><strong style=\"font-weight: 700; color: rgb(0, 0, 0); font-family: &quot;Times New Roman&quot;; font-size: medium; font-style: normal; font-variant-ligatures: normal; font-variant-caps: normal; letter-spacing: normal; orphans: 2; text-align: start; text-indent: 0px; text-transform: none; white-space: normal; widows: 2; word-spacing: 0px; -webkit-text-stroke-width: 0px; text-decoration-style: initial; text-decoration-color: initial;\">Éxodo 2:10</strong></p>\n<p><strong style=\"font-weight: 700; color: rgb(0, 0, 0); font-family: &quot;Times New Roman&quot;; font-size: medium; font-style: normal; font-variant-ligatures: normal; font-variant-caps: normal; letter-spacing: normal; orphans: 2; text-align: start; text-indent: 0px; text-transform: none; white-space: normal; widows: 2; word-spacing: 0px; -webkit-text-stroke-width: 0px; text-decoration-style: initial; text-decoration-color: initial;\">10&nbsp;</strong>Ya crecido el niño, se lo llevó a la hija del faraón, y ella lo adoptó como hijo suyo; además, le puso por nombre Moisés, pues dijo: «¡Yo lo saqué del río!»</p>\n<p><strong style=\"font-weight: 700; color: rgb(0, 0, 0); font-family: &quot;Times New Roman&quot;; font-size: medium; font-style: normal; font-variant-ligatures: normal; font-variant-caps: normal; letter-spacing: normal; orphans: 2; text-align: start; text-indent: 0px; text-transform: none; white-space: normal; widows: 2; word-spacing: 0px; -webkit-text-stroke-width: 0px; text-decoration-style: initial; text-decoration-color: initial;\">Amós 7:14</strong></p>\n<p><strong>14</strong> Amós le respondió a Amasías:</p>\n<p>—Yo no soy profeta ni hijo de profeta, sino que cuido ovejas y cultivo higueras.</p>\n<p><strong style=\"font-weight: 700; color: rgb(0, 0, 0); font-family: &quot;Times New Roman&quot;; font-size: medium; font-style: normal; font-variant-ligatures: normal; font-variant-caps: normal; letter-spacing: normal; orphans: 2; text-align: start; text-indent: 0px; text-transform: none; white-space: normal; widows: 2; word-spacing: 0px; -webkit-text-stroke-width: 0px; text-decoration-style: initial; text-decoration-color: initial;\">&nbsp;Jeremías 1:1-6</strong>&nbsp;</p>\n<p><strong>1&nbsp;</strong>Estas son las palabras de Jeremías hijo de Jilquías. Jeremías provenía de una familia sacerdotal de Anatot, ciudad del territorio de Benjamín.&nbsp;</p>\n<p><strong>2</strong> La palabra del Señor vino a Jeremías en el año trece del reinado de Josías hijo de Amón, rey de Judá<strong>.&nbsp;</strong></p>\n<p><strong>3</strong> También vino a él durante el reinado de Joacim hijo de Josías, rey de Judá, y hasta el fin del reinado de Sedequías hijo de Josías, rey de Judá; es decir, hasta el quinto mes del año undécimo de su reinado, cuando la población de Jerusalén fue deportada.</p>\n<p><strong>4</strong> La palabra del Señor vino a mí:</p>\n<p><strong>5</strong> «Antes de formarte en el vientre, ya te había elegido; antes de que nacieras, ya te había apartado; te había nombrado profeta para las naciones».</p>\n<p><strong>6</strong> Yo le respondí:</p>\n<p>«¡Ah, Señor mi Dios! ¡Soy muy joven, y no sé hablar!»</p>\n<p><strong style=\"font-weight: 700; color: rgb(0, 0, 0); font-family: &quot;Times New Roman&quot;; font-size: medium; font-style: normal; font-variant-ligatures: normal; font-variant-caps: normal; letter-spacing: normal; orphans: 2; text-align: start; text-indent: 0px; text-transform: none; white-space: normal; widows: 2; word-spacing: 0px; -webkit-text-stroke-width: 0px; text-decoration-style: initial; text-decoration-color: initial;\">Daniel 6:1-5</strong></p>\n<p><strong style=\"font-weight: 700; color: rgb(0, 0, 0); font-family: &quot;Times New Roman&quot;; font-size: medium; font-style: normal; font-variant-ligatures: normal; font-variant-caps: normal; letter-spacing: normal; orphans: 2; text-align: start; text-indent: 0px; text-transform: none; white-space: normal; widows: 2; word-spacing: 0px; -webkit-text-stroke-width: 0px; text-decoration-style: initial; text-decoration-color: initial;\">1&nbsp;</strong>Para el control eficaz de su reino, Darío consideró prudente nombrar a ciento veinte sátrapas</p>\n<p><strong style=\"font-weight: 700; color: rgb(0, 0, 0); font-family: &quot;Times New Roman&quot;; font-size: medium; font-style: normal; font-variant-ligatures: normal; font-variant-caps: normal; letter-spacing: normal; orphans: 2; text-align: start; text-indent: 0px; text-transform: none; white-space: normal; widows: 2; word-spacing: 0px; -webkit-text-stroke-width: 0px; text-decoration-style: initial; text-decoration-color: initial;\">2&nbsp;</strong>y tres administradores, uno de los cuales era Daniel. Estos sátrapas eran responsables ante los administradores, a fin de que los intereses del rey no se vieran afectados.&nbsp;</p>\n<p><strong style=\"font-weight: 700; color: rgb(0, 0, 0); font-family: &quot;Times New Roman&quot;; font-size: medium; font-style: normal; font-variant-ligatures: normal; font-variant-caps: normal; letter-spacing: normal; orphans: 2; text-align: start; text-indent: 0px; text-transform: none; white-space: normal; widows: 2; word-spacing: 0px; -webkit-text-stroke-width: 0px; text-decoration-style: initial; text-decoration-color: initial;\">3&nbsp;</strong>Y tanto se distinguió Daniel por sus extraordinarias cualidades administrativas que el rey pensó en ponerlo al frente de todo el reino.</p>\n<p><strong style=\"font-weight: 700; color: rgb(0, 0, 0); font-family: &quot;Times New Roman&quot;; font-size: medium; font-style: normal; font-variant-ligatures: normal; font-variant-caps: normal; letter-spacing: normal; orphans: 2; text-align: start; text-indent: 0px; text-transform: none; white-space: normal; widows: 2; word-spacing: 0px; -webkit-text-stroke-width: 0px; text-decoration-style: initial; text-decoration-color: initial;\">4&nbsp;</strong>Entonces los administradores y los sátrapas empezaron a buscar algún motivo para acusar a Daniel de malos manejos en los negocios del reino. Sin embargo, no encontraron de qué acusarlo porque, lejos de ser corrupto o negligente, Daniel era un hombre digno de confianza.</p>\n<p><strong style=\"font-weight: 700; color: rgb(0, 0, 0); font-family: &quot;Times New Roman&quot;; font-size: medium; font-style: normal; font-variant-ligatures: normal; font-variant-caps: normal; letter-spacing: normal; orphans: 2; text-align: start; text-indent: 0px; text-transform: none; white-space: normal; widows: 2; word-spacing: 0px; -webkit-text-stroke-width: 0px; text-decoration-style: initial; text-decoration-color: initial;\">5&nbsp;</strong>Por eso concluyeron: «Nunca encontraremos nada de qué acusar a Daniel, a no ser algo relacionado con la ley de su Dios».</p>\n<p><strong style=\"font-weight: 700; color: rgb(0, 0, 0); font-family: &quot;Times New Roman&quot;; font-size: medium; font-style: normal; font-variant-ligatures: normal; font-variant-caps: normal; letter-spacing: normal; orphans: 2; text-align: start; text-indent: 0px; text-transform: none; white-space: normal; widows: 2; word-spacing: 0px; -webkit-text-stroke-width: 0px; text-decoration-style: initial; text-decoration-color: initial;\">Mateo 9:9</strong></p>\n<p><strong style=\"font-weight: 700; color: rgb(0, 0, 0); font-family: &quot;Times New Roman&quot;; font-size: medium; font-style: normal; font-variant-ligatures: normal; font-variant-caps: normal; letter-spacing: normal; orphans: 2; text-align: start; text-indent: 0px; text-transform: none; white-space: normal; widows: 2; word-spacing: 0px; -webkit-text-stroke-width: 0px; text-decoration-style: initial; text-decoration-color: initial;\">9&nbsp;</strong>Al irse de allí, Jesús vio a un hombre llamado Mateo, sentado a la mesa de recaudación de impuestos. «Sígueme», le dijo. Mateo se levantó y lo siguió.</p>\n<p><strong style=\"font-weight: 700; color: rgb(0, 0, 0); font-family: &quot;Times New Roman&quot;; font-size: medium; font-style: normal; font-variant-ligatures: normal; font-variant-caps: normal; letter-spacing: normal; orphans: 2; text-align: start; text-indent: 0px; text-transform: none; white-space: normal; widows: 2; word-spacing: 0px; -webkit-text-stroke-width: 0px; text-decoration-style: initial; text-decoration-color: initial;\">Filipenses 3:3-6</strong></p>\n<p><strong style=\"font-weight: 700; color: rgb(0, 0, 0); font-family: &quot;Times New Roman&quot;; font-size: medium; font-style: normal; font-variant-ligatures: normal; font-variant-caps: normal; letter-spacing: normal; orphans: 2; text-align: start; text-indent: 0px; text-transform: none; white-space: normal; widows: 2; word-spacing: 0px; -webkit-text-stroke-width: 0px; text-decoration-style: initial; text-decoration-color: initial;\">3&nbsp;</strong>Porque la circuncisión somos nosotros, los que por medio del Espíritu de Dios adoramos, nos enorgullecemos en Cristo Jesús y no ponemos nuestra confianza en esfuerzos humanos.</p>\n<p><strong style=\"font-weight: 700; color: rgb(0, 0, 0); font-family: &quot;Times New Roman&quot;; font-size: medium; font-style: normal; font-variant-ligatures: normal; font-variant-caps: normal; letter-spacing: normal; orphans: 2; text-align: start; text-indent: 0px; text-transform: none; white-space: normal; widows: 2; word-spacing: 0px; -webkit-text-stroke-width: 0px; text-decoration-style: initial; text-decoration-color: initial;\">4&nbsp;</strong>Yo mismo tengo motivos para tal confianza. Si cualquier otro cree tener motivos para confiar en esfuerzos humanos, yo más:</p>\n<p><strong style=\"font-weight: 700; color: rgb(0, 0, 0); font-family: &quot;Times New Roman&quot;; font-size: medium; font-style: normal; font-variant-ligatures: normal; font-variant-caps: normal; letter-spacing: normal; orphans: 2; text-align: start; text-indent: 0px; text-transform: none; white-space: normal; widows: 2; word-spacing: 0px; -webkit-text-stroke-width: 0px; text-decoration-style: initial; text-decoration-color: initial;\">5&nbsp;</strong>circuncidado al octavo día, del pueblo de Israel, de la tribu de Benjamín, hebreo de pura cepa; en cuanto a la interpretación de la ley, fariseo;</p>\n<p><strong style=\"font-weight: 700; color: rgb(0, 0, 0); font-family: &quot;Times New Roman&quot;; font-size: medium; font-style: normal; font-variant-ligatures: normal; font-variant-caps: normal; letter-spacing: normal; orphans: 2; text-align: start; text-indent: 0px; text-transform: none; white-space: normal; widows: 2; word-spacing: 0px; -webkit-text-stroke-width: 0px; text-decoration-style: initial; text-decoration-color: initial;\">6&nbsp;</strong>en cuanto al celo, perseguidor de la iglesia; en cuanto a la justicia que la ley exige, intachable.</p>\n<p><strong style=\"font-weight: 700; color: rgb(0, 0, 0); font-family: &quot;Times New Roman&quot;; font-size: medium; font-style: normal; font-variant-ligatures: normal; font-variant-caps: normal; letter-spacing: normal; orphans: 2; text-align: start; text-indent: 0px; text-transform: none; white-space: normal; widows: 2; word-spacing: 0px; -webkit-text-stroke-width: 0px; text-decoration-style: initial; text-decoration-color: initial;\">Apocalipsis 1:9</strong></p>\n<p><strong style=\"font-weight: 700; color: rgb(0, 0, 0); font-family: &quot;Times New Roman&quot;; font-size: medium; font-style: normal; font-variant-ligatures: normal; font-variant-caps: normal; letter-spacing: normal; orphans: 2; text-align: start; text-indent: 0px; text-transform: none; white-space: normal; widows: 2; word-spacing: 0px; -webkit-text-stroke-width: 0px; text-decoration-style: initial; text-decoration-color: initial;\">9&nbsp;</strong>Yo, Juan, hermano de ustedes y compañero en el sufrimiento, en el reino y en la perseverancia que tenemos en unión con Jesús, estaba en la isla de Patmos por causa de la palabra de Dios y del testimonio de Jesús.</p>\n<p>La Biblia fue escrita por gente de diferentes orígenes y en diversas circunstancias. Algunos escribieron desde palacios; otros, desde cárceles; otros, en el exilio; y otros, en sus viajes misioneros para compartir el evangelio. Estas personas tenían diferentes formaciones y ocupaciones. Algunos, como Moisés, estaban destinados a ser reyes o, como Daniel, a ocupar altos cargos. Otros eran pastores sencillos. Algunos eran muy jóvenes; y otros, bastante ancianos. A pesar de estas diferencias, todos tenían algo en común: fueron llamados por Dios e inspirados por el Espíritu Santo con el fin de escribir mensajes para su pueblo, sin importar cuándo o dónde vivieran.</p>\n<p>Además, algunos de los autores fueron testigos presenciales de los acontecimientos relatados. Otros hicieron una investigación personal cuidadosa de los hechos o utilizaron cuidadosamente los documentos existentes (Jos. 10:13; Luc. 1:1-3). Pero, todas las partes de la Biblia son inspiradas (2 Tim. 3:16). Esta es la razón por la que Pablo declara que “las cosas que se escribieron antes, para nuestra enseñanza se escribieron, a fin de que por [...] la consolación de las Escrituras, tengamos esperanza” (Rom. 15:4). El Dios que creó el lenguaje humano capacita a los escogidos para comunicar pensamientos inspirados de manera confiable en palabras humanas.</p>\n<p>“Dios se ha dignado comunicar su verdad al mundo por medio de instrumentos humanos, y él mismo, mediante su Santo Espíritu, hizo idóneos a los hombres y los habilitó para realizar esa obra. Guio la mente de ellos en la elección de lo que debían decir y escribir. El tesoro fue confiado a vasos de barro; sin embargo, a pesar de todo, es del Cielo” (MS 1:29).</p>\n<p><span style=\"color: rgb(0, 0, 0);\"><strong>Tantos escritores diferentes, en contextos tan diversos y, sin embargo, el mismo Dios se revela a través de todos ellos. ¿Cómo nos ayuda esta asombrosa verdad a confirmar la veracidad de la Palabra de Dios?</strong></span></p>"
    },
    {
      "id": 14,
      "idLesson": 1,
      "idDay": 4,
      "dayTitle": "<p><strong>LA BIBLIA COMO PROFECÍA</strong></p>",
      "date": "31 de Marzo",
      "verses": [
        {
          "verse": "",
          "verseText": ""
        }
      ],
      "lessonText": "<p>La Biblia es única, entre otras obras religiosas famosas, porque hasta el treinta por ciento de su contenido se compone de profecías y literatura profética. La integración de la profecía y su cumplimiento oportuno es fundamental para la cosmovisión bíblica, porque el Dios que actúa en la historia también conoce el futuro y lo ha revelado a sus profetas (Amós 3:7). La Biblia no es solo la Palabra viva o la Palabra histórica, es la Palabra profética.</p>\n<p><strong>¿Cómo revelan los siguientes pasajes los detalles del Mesías venidero?</strong></p>\n<p><strong>Génesis 49:8-12&nbsp;</strong></p>\n<p><strong>8</strong> »Tú, Judá, serás alabado[a] por tus hermanos; dominarás a tus enemigos, y tus propios hermanos se inclinarán ante ti.</p>\n<p><strong>9</strong> Mi hijo Judá es como un cachorro de león que se ha nutrido de la presa. Se tiende al acecho como león, como leona que nadie se atreve a molestar.</p>\n<p><strong>10</strong> El cetro no se apartará de Judá, ni de entre sus pies el bastón de mando, hasta que llegue el verdadero rey,[b] quien merece la obediencia de los pueblos.</p>\n<p><strong>11</strong> Judá amarra su asno a la vid, y la cría de su asno a la mejor cepa; lava su ropa en vino; su manto, en la sangre de las uvas.</p>\n<p>&nbsp;<strong>12</strong> Sus ojos son más oscuros que el vino; sus dientes, más blancos que la leche.</p>\n<p><strong>Salmo 22:12-18</strong></p>\n<p><strong>12&nbsp;</strong>Muchos toros me rodean; fuertes toros de Basán me cercan.&nbsp;</p>\n<p><strong>13</strong> Contra mí abren sus fauces leones que rugen y desgarran a su presa.</p>\n<p><strong>14&nbsp;</strong>Como agua he sido derramado; dislocados están todos mis huesos. Mi corazón se ha vuelto como cera, y se derrite en mis entrañas.</p>\n<p><strong>15&nbsp;</strong>Se ha secado mi vigor como una teja; la lengua se me pega al paladar. ¡Me has hundido en el polvo de la muerte!</p>\n<p><strong>16&nbsp;</strong>Como perros de presa, me han rodeado; me ha cercado una banda de malvados; me han traspasado[a] las manos y los pies.&nbsp;</p>\n<p><strong>17&nbsp;</strong>Puedo contar todos mis huesos; con satisfacción perversa la gente se detiene a mirarme.</p>\n<p>&nbsp;<strong>18</strong> Se reparten entre ellos mis vestidos y sobre mi ropa echan suertes.&nbsp;</p>\n<p>&nbsp;<strong>Isaías 53:3-7</strong></p>\n<p><strong>3</strong> Despreciado y rechazado por los hombres, varón de dolores, hecho para el sufrimiento. Todos evitaban mirarlo; fue despreciado, y no lo estimamos.</p>\n<p><strong>4</strong> Ciertamente él cargó con nuestras enfermedades y soportó nuestros dolores, pero nosotros lo consideramos herido, golpeado por Dios, y humillado.&nbsp;</p>\n<p><strong>5</strong> Él fue traspasado por nuestras rebeliones, y molido por nuestras iniquidades; sobre él recayó el castigo, precio de nuestra paz, y gracias a sus heridas fuimos sanados.&nbsp;</p>\n<p><strong>6</strong> Todos andábamos perdidos, como ovejas; cada uno seguía su propio camino, pero el Señor hizo recaer sobre él la iniquidad de todos nosotros.</p>\n<p><strong>7</strong> Maltratado y humillado, ni siquiera abrió su boca; como cordero, fue llevado al matadero; como oveja, enmudeció ante su trasquilador; y ni siquiera abrió su boca.</p>\n<p><strong>Daniel 9:24-27</strong></p>\n<p><strong>24&nbsp;</strong>»”Setenta semanas[a] han sido decretadas para que tu pueblo y tu santa ciudad pongan fin a sus transgresiones y pecados, pidan perdón por su maldad, establezcan para siempre la justicia, sellen la visión y la profecía, y consagren el lugar santísimo.</p>\n<p><strong>25</strong> »”Entiende bien lo siguiente: Habrá siete semanas desde la promulgación del decreto que ordena la reconstrucción de Jerusalén hasta la llegada del príncipe elegido. Después de eso, habrá sesenta y dos semanas más. Entonces será reconstruida Jerusalén, con sus calles y murallas. Pero cuando los tiempos apremien,</p>\n<p><strong>26</strong> después de las sesenta y dos semanas, se le quitará la vida al príncipe elegido. Este se quedará sin ciudad y sin santuario, porque un futuro gobernante los destruirá. El fin vendrá como una inundación, y la destrucción no cesará hasta que termine la guerra.</p>\n<p><strong>27</strong> Durante una semana ese gobernante hará un pacto con muchos, pero a media semana pondrá fin a los sacrificios y ofrendas. Sobre una de las alas del templo cometerá horribles sacrilegios, hasta que le sobrevenga el desastroso fin que le ha sido decretado”».</p>\n<p>&nbsp;<strong>Miqueas 5:2</strong></p>\n<p><strong>2&nbsp;</strong>Pero de ti, Belén Efrata, pequeña entre los clanes de Judá, saldrá el que gobernará a Israel; sus orígenes se remontan hasta la antigüedad, hasta tiempos inmemoriales.</p>\n<p><strong>Malaquías 3:1</strong></p>\n<p><strong>1</strong> El Señor Todopoderoso responde: «Yo estoy por enviar a mi mensajero para que prepare el camino delante de mí. De pronto vendrá a su templo el Señor a quien ustedes buscan; vendrá el mensajero del pacto, en quien ustedes se complacen».</p>\n<p><strong>Zacarías 9:9</strong></p>\n<p><strong>9&nbsp;</strong>¡Alégrate mucho, hija de Sión! ¡Grita de alegría, hija de Jerusalén! Mira, tu rey viene hacia ti, justo, Salvador y humilde. Viene montado en un asno, en un pollino, cría de asna.&nbsp;</p>\n<p>Hay al menos 75 predicciones mesiánicas directas en el Antiguo Testamento, y muchas más si también agregamos la tipología (la tipología es el estudio de los rituales del Antiguo Testamento, como los sacrificios, que se consideran miniprofecías de Jesús). Estas profecías se relacionan con detalles específicos como: “No será quitado el cetro de Judá” (Gén. 49:10); que nacería en Belén de Judá (Miq. 5:2); que sería “despreciado y desechado entre los hombres”; azotado, acusado falsamente, pero sin abrir la boca para defenderse (Isa. 53:3-7); que sus manos y pies serían traspasados; y que se dividirían sus vestiduras entre sus verdugos (Sal. 22:12-18).</p>\n<p>El hecho de que estas profecías del Antiguo Testamento se hayan cumplido con tanta precisión en la vida, la muerte y la resurrección de Jesús es un testimonio de su inspiración y revelación divinas. También indica que Jesús era quien él y otros afirmaban que era. Jesús siguió a los profetas de la antigüedad al predecir su muerte y su resurrección (Luc. 9:21, 22; Mat. 17:22, 23), la caída de Jerusalén (Mat. 24:1, 2) y su segunda venida (Juan 14:1-3). Por lo tanto, la Biblia predice su encarnación, su muerte y su resurrección, y su cumplimiento garantiza su confiabilidad.</p>\n<p><strong><span style=\"color: rgb(0, 0, 0);\">¿Cuántas razones puedes enumerar por las que crees en Jesús y en su muerte en nuestro favor? Compártelas en clase el sábado y hazte esta pregunta: ¿Por qué las evidencias son tan convincentes?</span></strong></p>"
    },
    {
      "id": 15,
      "idLesson": 1,
      "idDay": 5,
      "dayTitle": "<p><strong>LA BIBLIA COMO HISTORIA</strong></p>",
      "date": "1 de Abril ",
      "verses": [
        {
          "verse": "",
          "verseText": ""
        }
      ],
      "lessonText": "<p>La Biblia es única en comparación con otros libros “santos” porque está constituida en la historia. Esto significa que la Biblia no es simplemente el pensamiento filosófico de un ser humano (como Confucio o Buda), ya que registra los actos de Dios en la historia al avanzar hacia un objetivo específico. En el caso de la Biblia, esos objetivos son: (1) la promesa de un Mesías y (2) la segunda venida de Jesús. Esta progresión es exclusiva de la fe judeocristiana, en contraste con la visión cíclica de muchas otras religiones del mundo desde el antiguo Egipto hasta las religiones orientales modernas.</p>\n<p><strong>Lee 1 Corintios 15:3 al 5 y 51 al 55; Romanos 8:11; y 1 Tesalonicenses 4:14. ¿Qué nos enseñan estos pasajes no solo sobre la verdad histórica de la resurrección de Cristo, sino también acerca de lo que significa para nosotros?</strong></p>\n<p><strong>1 Corintios 15:3 al 5</strong></p>\n<p><strong>3&nbsp;</strong>Porque ante todo[a] les transmití a ustedes lo que yo mismo recibí: que Cristo murió por nuestros pecados según las Escrituras,</p>\n<p><strong>4&nbsp;</strong>que fue sepultado, que resucitó al tercer día según las Escrituras,</p>\n<p><strong>5</strong> y que se apareció a Cefas, y luego a los doce.</p>\n<p><strong>1 Corintios &nbsp;15:51- 55</strong></p>\n<p><strong>51</strong> Fíjense bien en el misterio que les voy a revelar: No todos moriremos, pero todos seremos transformados,</p>\n<p><strong>52</strong> en un instante, en un abrir y cerrar de ojos, al toque final de la trompeta. Pues sonará la trompeta y los muertos resucitarán con un cuerpo incorruptible, y nosotros seremos transformados.</p>\n<p><strong>53</strong> Porque lo corruptible tiene que revestirse de lo incorruptible, y lo mortal, de inmortalidad.&nbsp;</p>\n<p><strong>54</strong> Cuando lo corruptible se revista de lo incorruptible, y lo mortal, de inmortalidad, entonces se cumplirá lo que está escrito: «La muerte ha sido devorada por la victoria».</p>\n<p><strong>55</strong> «¿Dónde está, oh muerte, tu victoria? ¿Dónde está, oh muerte, tu aguijón?»</p>\n<p><strong>Romanos 8:11</strong></p>\n<p><strong>11&nbsp;</strong>Y, si el Espíritu de aquel que levantó a Jesús de entre los muertos vive en ustedes, el mismo que levantó a Cristo de entre los muertos también dará vida a sus cuerpos mortales por medio de su Espíritu, que vive en ustedes.</p>\n<p><strong>1 Tesalonicenses 4:14.&nbsp;</strong></p>\n<p><strong>14&nbsp;</strong>¿Acaso no creemos que Jesús murió y resucitó? Así también Dios resucitará con Jesús a los que han muerto en unión con él.</p>\n<p>El testimonio de los cuatro evangelios y de Pablo es que Jesús murió, fue sepultado y resucitó de entre los muertos, y se les manifestó a varias personas. Esto lo corroboraron testigos oculares que lo colocaron en la tumba y luego la vieron vacía. Hubo testigos que tocaron a Jesús, y él comió con ellos. María Magdalena, María (la madre de Jesús) y otras mujeres lo vieron como el Cristo resucitado. Los discípulos hablaron con él camino a Emaús. Jesús se les apareció para la gran comisión evangélica. Pablo escribe que, si el testimonio de las Escrituras es rechazado, entonces nuestra predicación y nuestra fe son “vana[s]” (1 Cor. 15:14). Otras traducciones dicen “es inútil” (NTV), “carecen de sentido” (BLP) o “no sirve para nada” (NVI). Los discípulos afirman: “¡Es cierto! [...] El Señor ha resucitado” (Luc. 24:34, NVI). El término griego ontos se refiere a algo que realmente ocurrió. Se traduce como “realmente”, “de veras” o “verdaderamente”.</p>\n<p>Los discípulos declaran que “ha resucitado el Señor verdaderamente”. A Cristo también se lo describe como las “primicias” (1 Cor. 15:20) de todos los que murieron. El hecho histórico de que Cristo haya resucitado corporalmente de entre los muertos y esté vivo hoy es la garantía de que ellos también resucitarán así como él resucitó. Todos los justos “en Cristo [...] serán vivificados” (1 Cor. 15:22; énfasis añadido). Este término implica un acto futuro de creación, cuando aquellos “que son de Cristo” o que permanecen leales a él serán resucitados “en su venida” (1 Cor. 15:23) “a la final trompeta” (1 Cor. 15:52).</p>\n<p><strong><span style=\"color: rgb(0, 0, 0);\">¿Por qué es tan importante para nuestra fe la promesa de la resurrección, especialmente por el hecho de que entendemos que los muertos duermen? Sin ella, ¿por qué nuestra fe realmente es “vana”?</span></strong></p>"
    },
    {
      "id": 16,
      "idLesson": 1,
      "idDay": 6,
      "dayTitle": "<p><strong>EL PODER TRANSFORMADOR DE LA PALABRA</strong></p>",
      "date": "2 de Abril",
      "verses": [
        {
          "verse": "",
          "verseText": ""
        }
      ],
      "lessonText": "<p><strong>Lee 2 Reyes 22:3 al 20. ¿Qué hace que el rey Josías rasgue su ropa? ¿Cómo</strong></p>\n<p><strong>cambia su descubrimiento no solo a él, sino a toda la nación de Judá?</strong></p>\n<p><strong>2 Reyes 22:3 al 20.</strong></p>\n<p><strong>3</strong> En el año dieciocho de su reinado, el rey Josías mandó a su cronista Safán, hijo de Asalías y nieto de Mesulán, que fuera al templo del Señor. Le dijo:</p>\n<p><strong>4</strong> «Preséntate ante el sumo sacerdote Jilquías y encárgale que recoja el dinero que el pueblo ha llevado al templo del Señor y ha entregado a los porteros.&nbsp;</p>\n<p><strong>5</strong> Ordena que ahora se les entregue el dinero a los que supervisan la restauración del templo del Señor, para pagarles a los trabajadores que lo están reparando.</p>\n<p><strong>6</strong> Que les paguen a los carpinteros, a los maestros de obra y a los albañiles, y que compren madera y piedras de cantería para restaurar el templo.</p>\n<p><strong>7</strong> Pero no les pidan cuentas a los que están encargados de pagar, pues ellos proceden con toda honradez».</p>\n<p><strong>8</strong> El sumo sacerdote Jilquías le dijo al cronista Safán: «He encontrado el libro de la ley en el templo del Señor». Entonces se lo entregó a Safán, y este, después de leerlo,&nbsp;</p>\n<p><strong>9</strong> fue y le informó al rey:</p>\n<p>—Los ministros de Su Majestad han recogido el dinero[a] que estaba en el templo del Señor y se lo han entregado a los trabajadores y a los supervisores.</p>\n<p><strong>10</strong> El cronista Safán también le informó al rey que el sumo sacerdote Jilquías le había entregado un libro, el cual leyó en su presencia.</p>\n<p><strong>11</strong> Cuando el rey oyó las palabras del libro de la ley, se rasgó las vestiduras&nbsp;</p>\n<p><strong>12</strong> y dio esta orden a Jilquías el sacerdote, a Ajicán hijo de Safán, a Acbor hijo de Micaías, a Safán el cronista, y a Asaías, su ministro personal:</p>\n<p><strong>13</strong> —Vayan a consultar al Señor por mí, por el pueblo y por todo Judá con respecto a lo que dice este libro que se ha encontrado. Sin duda que la gran ira del Señor arde contra nosotros, porque nuestros antepasados no obedecieron lo que dice este libro ni actuaron según lo que está prescrito para nosotros.</p>\n<p><strong>14</strong> Así que Jilquías el sacerdote, Ajicán, Acbor, Safán y Asaías fueron a consultar a la profetisa Huldá, que vivía en el barrio nuevo de Jerusalén. Huldá era la esposa de Salún, el encargado del vestuario, quien era hijo de Ticvá y nieto de Jarjás.</p>\n<p><strong>15</strong> Huldá les contestó: «Así dice el Señor, Dios de Israel: “Díganle al que los ha enviado&nbsp;</p>\n<p><strong>16</strong> que yo, el Señor, les advierto: ‘Voy a enviar desgracia sobre este lugar y sus habitantes, según todo lo que dice el libro que ha leído el rey de Judá.</p>\n<p><strong>17</strong> Ellos me han abandonado; han quemado incienso a otros dioses y me han provocado a ira con todos sus ídolos. Por eso mi ira arde contra este lugar, y no se apagará’.</p>\n<p><strong>18</strong> Pero al rey de Judá, que los envió para consultarme, díganle que en lo que atañe a las palabras que él ha oído, yo, el Señor, Dios de Israel, afirmo:</p>\n<p><strong>19</strong> ‘Como te has conmovido y humillado ante el Señor al escuchar lo que he anunciado contra este lugar y sus habitantes, que serían asolados y malditos; y, como te has rasgado las vestiduras y has llorado en mi presencia, yo te he escuchado. Yo, el Señor, lo afirmo.&nbsp;</p>\n<p><strong>20</strong> Por lo tanto, te reuniré con tus antepasados, y serás sepultado en paz. Tus ojos no verán la desgracia que enviaré sobre este lugar’ ”». Así que ellos regresaron para informar al rey.</p>\n<p>En 621 a.C., cuando Josías tenía aproximadamente 25 años, Hilcías, el sumo sacerdote, descubrió “el libro de la ley”, que pudieron haber sido los primeros cinco libros de Moisés o, específicamente, el libro de Deuteronomio. Durante el reinado de su padre Amón y su malvado abuelo Manasés, este rollo se había perdido en medio de la adoración a Baal, Asera y “todo el ejército de los cielos” (2 Rey. 21:3-9). Cuando Josías oyó las condiciones del Pacto, se rasgó la ropa totalmente angustiado, ya que se dio cuenta de cuán lejos se habían apartado él y su pueblo de la adoración al Dios verdadero. Inmediatamente comenzó una reforma en toda la tierra, derribando los lugares altos y destruyendo imágenes a los dioses extranjeros. Al terminar, solo quedaba un lugar para adorar en Judá: el templo de Dios en Jerusalén. El descubrimiento de la Palabra de Dios lleva a la convicción, al arrepentimiento y al poder para cambiar. Este cambio comienza con Josías y, finalmente, se extiende al resto de Judá.</p>\n<p><strong>¿Cómo nos garantiza la Biblia que tiene el poder de cambiar nuestra&nbsp;</strong><strong>vida y mostrarnos el camino de la salvación? Lee Juan 16:13; 17:17; Hebreos&nbsp;</strong><strong>4:12; y Romanos 12:2.</strong></p>\n<p><strong>Juan 16:13</strong></p>\n<p><strong>13&nbsp;</strong>Pero, cuando venga el Espíritu de la verdad, él los guiará a toda la verdad, porque no hablará por su propia cuenta, sino que dirá solo lo que oiga y les anunciará las cosas por venir.</p>\n<p><strong>Juan 17:17</strong></p>\n<p><strong>17&nbsp;</strong>Santifícalos en la verdad; tu palabra es la verdad.</p>\n<p><strong>Hebreos&nbsp;4:12</strong></p>\n<p><strong>12&nbsp;</strong>Ciertamente, la palabra de Dios es viva y poderosa, y más cortante que cualquier espada de dos filos. Penetra hasta lo más profundo del alma y del espíritu, hasta la médula de los huesos, y juzga los pensamientos y las intenciones del corazón.</p>\n<p><strong>Romanos 12:2</strong></p>\n<p><strong>2&nbsp;</strong>No se amolden al mundo actual, sino sean transformados mediante la renovación de su mente. Así podrán comprobar cuál es la voluntad de Dios, buena, agradable y perfecta.</p>\n<p>Uno de los testimonios más poderosos del poder de la Biblia es la vida transformada de una persona. Es la Palabra la que traspone el pecado humano y la depravación, y revela nuestra verdadera naturaleza humana y nuestra necesidad de un Salvador.</p>\n<p>Un libro único como la Biblia, instaurado en la historia, imbuido de profecía y con el poder de transformar vidas, también debe interpretarse de una manera única. No puede interpretarse como cualquier otro libro, ya que la Palabra viva de Dios debe entenderse a la luz de un Cristo vivo que prometió enviar a su Espíritu para guiarnos “a toda la verdad” (Juan 16:13). Por lo tanto, la Biblia como una revelación de la verdad de Dios, debe contener sus propios principios internos de interpretación. Estos principios se pueden encontrar al estudiar de qué manera los escritores bíblicos utilizaron las Escrituras y se guiaron por ellas mientras permitían que las Escrituras se interpretaran a sí mismas.</p>"
    },
    {
      "id": 17,
      "idLesson": 1,
      "idDay": 7,
      "dayTitle": "",
      "date": "3 de Abril",
      "verses": [
        {
          "verse": "",
          "verseText": ""
        }
      ],
      "lessonText": "<p><strong>PARA ESTUDIAR Y MEDITAR:</strong></p>\n<p>&nbsp;Lee Elena de White, El Deseado de todas las gentes, “No se turbe vuestro corazón”, pp. 617-635.</p>\n<p>Muchos han muerto por defender la Palabra de Dios y permanecer fieles a ella. Uno de ellos fue el Dr. Rowland Taylor, un pastor parroquial inglés que se resistió a la imposición de la misa católica durante el reinado de María la Sanguinaria en su parroquia de Hadley, Inglaterra. Después de ser expulsado de la iglesia y ridiculizado por su adhesión a las Escrituras, apeló personalmente al obispo de Wínchester, al Señor Canciller de Inglaterra, pero este lo mandó a la cárcel y finalmente a la hoguera. Justo antes de su muerte, en 1555, pronunció estas palabras:</p>\n<p>“¡Buena gente! No les he enseñado nada más que la santa Palabra de Dios, y esas lecciones que he extraído del bendito libro de Dios, la Santa Biblia. He venido aquí este día para sellarlo con mi sangre” (J. Foxe, The New Foxe’s Book of Martyrs, p. 193). Justo antes de que se encendiera el fuego se escuchó al Dr. Taylor repetir el Salmo 51 y entregó su vida.</p>\n<p>La pregunta que debemos hacernos ahora es: ¿Seremos tan fieles para defender las verdades de la Palabra de Dios? Tarde o temprano, en el conflicto final, esa prueba vendrá. El momento de prepararse para ello, por supuesto, es ahora.</p>\n<p><strong>PREGUNTAS PARA DIALOGAR:</strong></p>\n<p><strong>1. </strong>¿De qué manera la profecía confirma el origen divino de la Biblia? ¿Cómo pueden afirmarnos en nuestra fe estas profecías cumplidas?</p>\n<p><strong>2.</strong> En cuanto a la pregunta final del estudio del martes, ¿por qué son tan poderosas las evidencias de Jesús como Mesías?</p>\n<p><strong>3</strong>. Jesús y los apóstoles demostraron una fe inquebrantable en la veracidad y la autoridad divina de las Sagradas Escrituras. Por ejemplo, ¿cuántas veces se refirió Jesús a las Escrituras y a que (a menudo en referencia a él mismo) las Escrituras deben cumplirse? (ver, p. ej., Mat. 26:54, 56; Mar. 14:49; Luc. 4:21; Juan 13:18; 17:12). Por lo tanto, si Jesús mismo consideraba las Escrituras (en su caso, el Antiguo Testamento) con tanta seriedad, especialmente en términos de la profecía que se estaba cumpliendo, ¿cuál debería ser nuestra actitud hacia la Biblia también?</p>"
    }
  ]
}